{
  "noDescription": "ไม่มีคำอธิบาย",
  "information.name": "ข้อมูล",
  "information.description": "ใช้แสดงข้อมูลต่าง ๆ",
  "information.options.bot.name": "บอท",
  "information.options.bot.description": "แสดงข้อมูลเกี่ยวกับบอท",
  "information.options.bot.strings.concept.title": "โรสต์คืออะไร",
  "information.options.bot.strings.concept.description": "**Rost** เป็นบอทอย่างเป็นทางการที่ดูแล **{server_name}** ซึ่งเป็นชุมชน Discord ที่ใหญ่ที่สุดที่มุ่งเน้นการเรียนรู้ภาษาโรมาเนีย",
  "information.options.bot.strings.function.title": "โรสต์ทำอะไร?",
  "information.options.bot.strings.function.description": "ดูแลความต้องการด้านการบริหารและการจัดการของชุมชน รวมถึงแต่ไม่จำกัดเพียง:",
  "information.options.bot.strings.function.features.information": "การโพสต์และรักษาข้อมูลสำคัญไว้ทั่วชุมชน",
  "information.options.bot.strings.function.features.moderation": "เครื่องมือการควบคุม, รวมถึงการตรวจสอบผู้ใช้, รายงานผู้ใช้, ระบบเตือน + ให้อภัย, โหมดช้าที่สามารถปรับแต่งได้, การลบข้อความ, การอ้างอิงกฎ, การดูนโยบาย, และอื่น ๆ.",
  "information.options.bot.strings.function.features.roles": "การจัดการบทบาทที่ใช้งานง่ายและเป็นเอกลักษณ์ด้วยเมนูการเลือกบทบาทที่คล้ายกับโฟลเดอร์",
  "information.options.bot.strings.function.features.music": "การเล่นเสียงพร้อมการจัดการแทร็กขั้นสูง, การจัดการคิวและประวัติ, รองรับเพลย์ลิสต์ระดับพรีเมียม, และอื่น ๆ",
  "information.options.bot.strings.function.features.social": "คุณสมบัติทางสังคม รวมถึงการดูโปรไฟล์ผู้ใช้ และการขอบคุณผู้ใช้สำหรับการมีส่วนร่วมของพวกเขา",
  "information.options.server.name": "เซิร์ฟเวอร์",
  "information.options.server.description": "แสดงข้อมูลเกี่ยวกับเซิร์ฟเวอร์",
  "information.options.server.strings.information.title": "ข้อมูลเกี่ยวกับ {server_name}",
  "information.options.server.strings.information.description.description": "คำอธิบาย",
  "information.options.server.strings.information.description.noDescription": "ไม่มีการระบุคำอธิบาย",
  "information.options.server.strings.information.description.members": "สมาชิก",
  "information.options.server.strings.information.description.created": "สร้างขึ้น",
  "information.options.server.strings.information.description.channels": "ช่องทาง",
  "information.options.server.strings.information.description.languages": "ภาษา",
  "information.options.server.strings.information.description.owner": "เจ้าของ",
  "information.options.server.strings.information.description.moderators": "ผู้ดูแล",
  "information.options.server.strings.information.description.overseenByModerators": "เซิร์ฟเวอร์นี้อยู่ภายใต้การดูแลของกลุ่มผู้นำทาง",
  "information.options.server.strings.information.description.distribution": "การกระจายความสามารถทางภาษาของสมาชิก",
  "information.options.server.strings.information.description.withoutProficiency": "โดยไม่มีข้อกำหนดด้านความสามารถทางภาษา",
  "information.options.server.strings.channelTypes.text": "ข้อความ",
  "information.options.server.strings.channelTypes.voice": "เสียง",
  "information.options.server.strings.languageTypes.home": "หน้าแรก",
  "information.options.server.strings.languageTypes.target": "เป้าหมาย",
  "list.name": "รายการ",
  "list.description": "อนุญาตให้ดูข้อมูลต่าง ๆ เกี่ยวกับผู้ใช้",
  "list.options.warnings.name": "คำเตือน",
  "list.options.warnings.description": "แสดงรายการคำเตือนที่ออกให้กับผู้ใช้",
  "list.options.warnings.strings.failed.title": "ไม่สามารถแสดงคำเตือนได้",
  "list.options.warnings.strings.failed.description": "ไม่สามารถแสดงคำเตือนสำหรับผู้ใช้ที่ระบุได้",
  "list.options.warnings.strings.noActiveWarnings.title": "ไม่มีคำเตือนที่ใช้งานอยู่",
  "list.options.warnings.strings.noActiveWarnings.description.self": "คุณไม่มีคำเตือนที่ใช้งานอยู่",
  "list.options.warnings.strings.noActiveWarnings.description.other": "ผู้ใช้รายนี้ไม่มีคำเตือนใด ๆ ที่กำลังดำเนินการอยู่",
  "list.options.warnings.strings.warnings.title": "คำเตือน",
  "list.options.warnings.strings.warnings.description.warning": "คำเตือน #{index}, ตามเวลา {relative_timestamp}",
  "list.options.praises.name": "คำสรรเสริญ",
  "list.options.praises.description": "อนุญาตให้ดูคำชมเชยของผู้ใช้",
  "list.options.praises.options.author.name": "ผู้แต่ง",
  "list.options.praises.options.author.description": "แสดงรายการคำชมเชยที่ผู้ใช้ได้รับ",
  "list.options.praises.options.target.name": "เป้าหมาย",
  "list.options.praises.options.target.description": "แสดงรายการคำชมที่มอบให้กับผู้ใช้",
  "list.options.praises.strings.failed.title": "ไม่สามารถแสดงความชื่นชมได้",
  "list.options.praises.strings.failed.description": "ไม่สามารถแสดงความชื่นชมให้กับผู้ใช้ที่ระบุได้",
  "list.options.praises.strings.noPraises.title": "ไม่มีคำชม",
  "list.options.praises.strings.noPraises.description.self.author": "คุณยังไม่ได้ให้คำชมเชยใดๆ เลย",
  "list.options.praises.strings.noPraises.description.self.target": "คุณไม่ได้รับคำชมเชยใด ๆ",
  "list.options.praises.strings.noPraises.description.other.author": "ผู้ใช้รายนี้ยังไม่ได้ให้คำชมใดๆ",
  "list.options.praises.strings.noPraises.description.other.target": "ผู้ใช้รายนี้ยังไม่ได้รับคำชมใดๆ",
  "list.options.praises.strings.praises.title": "คำสรรเสริญ",
  "list.options.praises.strings.praises.noComment": "ไม่มีคำอธิบายเพิ่มเติม",
  "pardon.name": "ขอโทษ",
  "pardon.description": "ลบคำเตือนหนึ่งข้อที่เคยแจ้งให้ผู้ใช้ทราบก่อนหน้านี้",
  "pardon.options.warning.name": "คำเตือน",
  "pardon.options.warning.description": "คำเตือนให้ลบ",
  "pardon.strings.failed.title": "ไม่สามารถลบคำเตือนได้",
  "pardon.strings.failed.description": "เนื่องจากสาเหตุที่ไม่ทราบได้ การลบคำเตือนที่ระบุไว้ล้มเหลว",
  "pardon.strings.invalidWarning.title": "คำเตือนไม่ถูกต้อง",
  "pardon.strings.invalidWarning.description": "คำเตือนที่คุณระบุไม่ถูกต้อง",
  "pardon.strings.pardoned.title": "ผู้ใช้ได้รับการอภัยโทษ",
  "pardon.strings.pardoned.description": "ผู้ใช้ {user_mention} ได้รับการอภัยโทษจากการเตือนสำหรับ: {reason}",
  "policy.name": "นโยบาย",
  "policy.description": "แสดงนโยบายการตรวจสอบของเซิร์ฟเวอร์",
  "purge.name": "ล้าง",
  "purge.description": "ลบข้อความจำนวนหนึ่งออกจากช่อง",
  "purge.options.start.name": "เริ่มต้น",
  "purge.options.start.description": "รหัสของข้อความที่จุดเริ่มต้นของช่วง",
  "purge.options.end.name": "จบ",
  "purge.options.end.description": "รหัสของข้อความที่สิ้นสุดของช่วง",
  "purge.options.author.name": "ผู้แต่ง",
  "purge.options.author.description": "ผู้ใช้ที่ต้องการลบข้อความ",
  "purge.strings.invalid.start.title": "ข้อความเริ่มต้นไม่ถูกต้อง",
  "purge.strings.invalid.start.description": "รหัสข้อความเริ่มต้นที่คุณให้มาไม่ถูกต้อง",
  "purge.strings.invalid.end.title": "ข้อความสิ้นสุดไม่ถูกต้อง",
  "purge.strings.invalid.end.description": "รหัสข้อความตอนท้ายที่คุณให้มาไม่ถูกต้อง",
  "purge.strings.invalid.both.title": "รหัสไม่ถูกต้อง",
  "purge.strings.invalid.both.description": "รหัสข้อความเริ่มต้นและสิ้นสุดที่คุณให้มาไม่ถูกต้อง",
  "purge.strings.idsNotDifferent.title": "ข้อความเริ่มต้นและข้อความสิ้นสุดเหมือนกัน",
  "purge.strings.idsNotDifferent.description": "ข้อความตอนท้ายอาจไม่เหมือนกับข้อความตอนเริ่มต้น",
  "purge.strings.failed.title": "ไม่สามารถล้างข้อมูลได้",
  "purge.strings.failed.description": "เนื่องจากสาเหตุที่ไม่ทราบได้ การล้างข้อความจากช่องทางนี้ล้มเหลว",
  "purge.strings.indexing.title": "กำลังจัดทำดัชนีข้อความ...",
  "purge.strings.indexing.description": "บอทกำลังจัดทำดัชนีข้อความที่อยู่ในช่วงที่คุณระบุไว้",
  "purge.strings.indexed.title": "เสร็จสิ้นการจัดทำดัชนี",
  "purge.strings.indexed.description.some": "บอทได้จัดทำดัชนีข้อความที่อยู่ในช่วงที่คุณระบุไว้ และพบ **{messages}**.",
  "purge.strings.indexed.description.some.messages.one": "{หนึ่ง} ข้อความที่ลบได้",
  "purge.strings.indexed.description.some.messages.two": "{สอง} ข้อความที่ลบได้",
  "purge.strings.indexed.description.some.messages.many": "{หลาย} ข้อความที่ลบได้",
  "purge.strings.indexed.description.none": "บอทได้จัดทำดัชนีข้อความที่อยู่ในช่วงที่คุณระบุไว้ และไม่พบข้อความที่สามารถลบได้",
  "purge.strings.indexed.description.tryDifferentQuery": "ลองใช้คำสั่งค้นหาอื่น",
  "purge.strings.indexed.description.tooMany": "บอทได้จัดทำดัชนีข้อความที่อยู่ในช่วงที่คุณระบุไว้ และพบ **{messages}** ซึ่งมากกว่า **จำนวนข้อความสูงสุดที่สามารถลบได้ในหนึ่งการล้างข้อมูลที่กำหนด ({maximum_deletable})**",
  "purge.strings.indexed.description.tooMany.messages.one": "{หนึ่ง} ข้อความที่ลบได้",
  "purge.strings.indexed.description.tooMany.messages.two": "{สอง} ข้อความที่ลบได้",
  "purge.strings.indexed.description.tooMany.messages.many": "{หลาย} ข้อความที่ลบได้",
  "purge.strings.indexed.description.limited": "หากคุณเลือกที่จะดำเนินการต่อ **{ข้อความ}** จะถูกลบแทน",
  "purge.strings.indexed.description.limited.messages.one": "{หนึ่ง} ข้อความ",
  "purge.strings.indexed.description.limited.messages.two": "{สอง} ข้อความ",
  "purge.strings.indexed.description.limited.messages.many": "{หลาย} ข้อความ",
  "purge.strings.sureToPurge.title": "แน่ใจว่าจะล้าง?",
  "purge.strings.sureToPurge.description": "ระหว่างการล้างข้อมูล **{ข้อความ}** จะถูกลบอย่างถาวรจาก {channel_mention}.",
  "purge.strings.sureToPurge.description.messages.one": "{หนึ่ง} ข้อความ",
  "purge.strings.sureToPurge.description.messages.two": "{สอง} ข้อความ",
  "purge.strings.sureToPurge.description.messages.many": "{หลาย} ข้อความ",
  "purge.strings.continue.title": "ดำเนินการต่อ?",
  "purge.strings.continue.description": "ระหว่างการล้างข้อมูล **{ข้อความ}** จะถูกลบอย่างถาวรจาก {channel_mention} ซึ่งเป็นเพียงส่วนหนึ่งของ {all_messages} ที่พบเท่านั้น",
  "purge.strings.continue.description.messages.one": "{หนึ่ง} ข้อความ",
  "purge.strings.continue.description.messages.two": "{สอง} ข้อความ",
  "purge.strings.continue.description.messages.many": "{หลาย} ข้อความ",
  "purge.strings.continue.description.allMessages.one": "{หนึ่ง} ข้อความ",
  "purge.strings.continue.description.allMessages.two": "{สอง} ข้อความ",
  "purge.strings.continue.description.allMessages.many": "{หลาย} ข้อความ",
  "purge.strings.purging.title": "กำลังล้างข้อมูล...",
  "purge.strings.purging.description.purging": "{ข้อความ} จาก {การกล่าวถึงช่อง}.",
  "purge.strings.purging.description.purging.messages.one": "{หนึ่ง} ข้อความกำลังถูกลบ",
  "purge.strings.purging.description.purging.messages.two": "{สอง} ข้อความกำลังถูกลบ",
  "purge.strings.purging.description.purging.messages.many": "{หลาย} ข้อความกำลังถูกลบ",
  "purge.strings.purging.description.mayTakeTime": "อาจใช้เวลาสักครู่",
  "purge.strings.purging.description.onceComplete": "เมื่อเสร็จสิ้นแล้ว คุณจะพบข้อความความสำเร็จในช่องบันทึก",
  "purge.strings.purged.title": "ล้างข้อมูลสำเร็จ",
  "purge.strings.purged.description": "{ข้อความ} จาก {การกล่าวถึงช่อง}.",
  "purge.strings.purged.description.messages.one": "{หนึ่ง} ข้อความถูกลบแล้ว",
  "purge.strings.purged.description.messages.two": "{สอง} ข้อความถูกลบแล้ว",
  "purge.strings.purged.description.messages.many": "{หลาย} ข้อความถูกลบไปแล้ว",
  "purge.strings.rangeTooBig.title": "ระยะทางไกลเกินไป",
  "purge.strings.rangeTooBig.description.rangeTooBig": "ขณะที่กำลังทำดัชนีช่วงข้อความที่เลือกไว้ บอทพบข้อความมากกว่า **{messages}** ซึ่งถือเป็นช่วงที่ใหญ่เกินไป",
  "purge.strings.rangeTooBig.description.rangeTooBig.messages.one": "{หนึ่ง} ข้อความ",
  "purge.strings.rangeTooBig.description.rangeTooBig.messages.two": "{สอง} ข้อความ",
  "purge.strings.rangeTooBig.description.rangeTooBig.messages.many": "{หลาย} ข้อความ",
  "purge.strings.rangeTooBig.description.trySmaller": "ลองเลือกช่วงข้อความที่ต้องการลบออกให้น้อยลง",
  "purge.strings.start": "เริ่มต้นข้อความ",
  "purge.strings.end": "สิ้นสุดข้อความ",
  "purge.strings.noContent": "ไม่มีเนื้อหา",
  "purge.strings.embedPosted": "ฝังโพสต์ {relative_timestamp} โดย {user_mention}",
  "purge.strings.posted": "โพสต์เมื่อ {relative_timestamp} โดย {user_mention}",
  "purge.strings.messagesFound": "พบข้อความ",
  "purge.strings.yes": "ใช่",
  "purge.strings.no": "ไม่มี",
  "report.name": "รายงาน",
  "report.description": "อนุญาตให้ผู้ใช้สร้างรายงานผู้ใช้",
  "report.strings.submitted.title": "รายงานถูกส่งแล้ว!",
  "report.strings.submitted.description": "รายงานของคุณได้ถูกส่งแล้ว รายงานจะถูกตรวจสอบโดยทีมงานเซิร์ฟเวอร์ แต่คุณจะไม่ได้รับการแจ้งเตือนโดยตรงเกี่ยวกับผลลัพธ์ของรายงานใด ๆ",
  "report.strings.failed.title": "ไม่สามารถส่งรายงานได้",
  "report.strings.failed.description": "เนื่องจากสาเหตุที่ไม่ทราบ, การส่งรายงานล้มเหลว.",
  "report.strings.sureToCancel.title": "แน่ใจว่าจะออกหรือไม่?",
  "report.strings.sureToCancel.description": "คุณแน่ใจหรือไม่ว่าต้องการหยุดส่งรายงานของคุณ?",
  "report.strings.tooMany.title": "รายงานมากเกินไป",
  "report.strings.tooMany.description": "คุณได้ทำรายงานไปแล้วไม่กี่ฉบับเมื่อเร็ว ๆ นี้ ก่อนที่จะส่งรายงานอีกครั้ง คุณควรรอสักครู่",
  "rule.name": "กฎ",
  "rule.description": "อ้างถึงกฎของเซิร์ฟเวอร์",
  "rule.options.rule.name": "กฎ",
  "rule.options.rule.description": "กฎในการอ้างอิง",
  "rule.strings.invalid.title": "กฎไม่ถูกต้อง",
  "rule.strings.invalid.description": "กฎที่คุณระบุไว้ไม่ถูกต้อง",
  "slowmode.name": "โหมดช้า",
  "slowmode.description": "สลับโหมดช้าสำหรับช่องที่คำสั่งนี้ถูกเรียกใช้",
  "slowmode.options.level.name": "ระดับ",
  "slowmode.options.level.description": "ระดับของโหมดช้าที่จะใช้",
  "slowmode.strings.levels.lowest": "ไม่เป็นไร (ต่ำสุด, 5 วินาที)",
  "slowmode.strings.levels.low": "มันเล็กน้อย (ต่ำ, 10 วินาที)",
  "slowmode.strings.levels.medium": "มันเริ่มเป็นปัญหาแล้ว (ปานกลาง, 30 วินาที)",
  "slowmode.strings.levels.high": "มันรุนแรง (ระดับสูง, 1 นาที)",
  "slowmode.strings.levels.highest": "เรื่องมันเริ่มวุ่นวายแล้ว (สูงสุด, 5 นาที)",
  "slowmode.strings.levels.emergency": "เป็นเหตุฉุกเฉิน (เหตุฉุกเฉิน, 20 นาที)",
  "slowmode.strings.levels.lockdown": "เราต้องล็อกสถานที่ (ล็อกดาวน์ 1 ชั่วโมง)",
  "slowmode.strings.levels.beyond": "มันไปถึงระดับต่อไปแล้ว (เกินกว่า 1 วัน)",
  "slowmode.strings.tooSoon.title": "ไม่สามารถปิดการใช้งานเร็วเกินไป",
  "slowmode.strings.tooSoon.description.justEnabled": "โหมดช้าได้ถูกเปิดใช้งานเมื่อสักครู่ที่ผ่านมา",
  "slowmode.strings.tooSoon.description.canDisableIn": "คุณจะสามารถปิดการใช้งานได้ {relative_timestamp}",
  "slowmode.strings.invalid.title": "ระดับไม่ถูกต้อง",
  "slowmode.strings.invalid.description": "ระดับที่คุณระบุไม่ถูกต้อง",
  "slowmode.strings.enabled.title": "โหมดช้าเปิดใช้งานอยู่",
  "slowmode.strings.enabled.description": "โหมดช้าได้ถูกเปิดใช้งานสำหรับช่องนี้",
  "slowmode.strings.disabled.title": "โหมดช้าไม่ทำงานแล้ว",
  "slowmode.strings.disabled.description": "โหมดช้าถูกปิดใช้งานสำหรับช่องนี้",
  "slowmode.strings.upgraded.title": "ระดับโหมดช้าได้รับการอัปเกรด",
  "slowmode.strings.upgraded.description": "ระดับโหมดช้าได้รับการอัปเกรดเป็นความรุนแรงที่สูงขึ้น",
  "slowmode.strings.downgraded.title": "ระดับโหมดช้าถูกลดระดับ",
  "slowmode.strings.downgraded.description": "ระดับโหมดช้าได้ถูกลดระดับความรุนแรงลงแล้ว",
  "slowmode.strings.theSame.title": "ระดับโหมดช้าเท่าเดิม",
  "slowmode.strings.theSame.description.theSame": "ระดับโหมดช้าปัจจุบันเท่ากับระดับที่ร้องขอ",
  "slowmode.strings.theSame.description.chooseDifferent": "เลือกระดับที่ต่างกัน",
  "timeout.name": "หมดเวลา",
  "timeout.description": "ใช้จัดการการหมดเวลาของผู้ใช้",
  "timeout.options.set.name": "ตั้ง",
  "timeout.options.set.description": "ผู้ใช้ถูกออฟไลน์ ทำให้ไม่สามารถโต้ตอบบนเซิร์ฟเวอร์ได้",
  "timeout.options.clear.name": "ชัดเจน",
  "timeout.options.clear.description": "ล้างการหมดเวลาของผู้ใช้",
  "timeout.strings.durationInvalid.title": "ระยะเวลาไม่ถูกต้อง",
  "timeout.strings.durationInvalid.description": "ระยะเวลาที่คุณระบุไม่ถูกต้อง",
  "timeout.strings.tooShort.title": "เวลาหมดเร็วเกินไป",
  "timeout.strings.tooShort.description": "การหมดเวลาต้องใช้เวลาอย่างน้อยหนึ่งนาที",
  "timeout.strings.tooLong.title": "หมดเวลา",
  "timeout.strings.tooLong.description": "ระยะเวลาต้องไม่เกินหนึ่งสัปดาห์",
  "timeout.strings.timedOut.title": "ผู้ใช้หมดเวลา",
  "timeout.strings.timedOut.description": "ผู้ใช้ {user_mention} ถูกหมดเวลาแล้ว การหมดเวลาจะหมดอายุใน {relative_timestamp}",
  "timeout.strings.notTimedOut.title": "ผู้ใช้ยังไม่หมดเวลา",
  "timeout.strings.notTimedOut.description": "ผู้ใช้ {user_mention} ยังไม่หมดเวลา",
  "timeout.strings.timeoutCleared.title": "หมดเวลาแล้ว",
  "timeout.strings.timeoutCleared.description": "ผู้ใช้ {user_mention} ไม่ถูกตัดการเชื่อมต่ออีกต่อไป",
  "warn.name": "เตือน",
  "warn.description": "เตือนผู้ใช้",
  "warn.options.rule.name": "กฎ",
  "warn.options.rule.description": "กฎที่ถูกอ้างว่าถูกละเมิด",
  "warn.options.rule.strings.other": "อื่นๆ (มีเหตุผลสนับสนุน)",
  "warn.strings.invalidRule.title": "กฎไม่ถูกต้อง",
  "warn.strings.invalidRule.description": "กฎที่คุณระบุไว้ไม่ถูกต้อง",
  "warn.strings.failed.title": "ไม่สามารถเตือนผู้ใช้ได้",
  "warn.strings.failed.description": "เนื่องจากสาเหตุที่ไม่ทราบ การแจ้งเตือนผู้ใช้ที่ระบุล้มเหลว",
  "warn.strings.warned.title": "ผู้ใช้ได้รับการเตือน",
  "warn.strings.warned.description": "ผู้ใช้ {user_mention} ได้รับการเตือนแล้ว ขณะนี้มี {warnings}",
  "warn.strings.warned.description.warnings.one": "{หนึ่ง} เตือน",
  "warn.strings.warned.description.warnings.two": "คำเตือน {สอง}",
  "warn.strings.warned.description.warnings.many": "{หลาย} คำเตือน",
  "warn.strings.limitReached.title": "ถึงขีดจำกัดเตือน",
  "warn.strings.limitReached.description": "{user_mention} ได้ถึงขีดจำกัดคำเตือนแล้ว ({limit})",
  "warn.strings.limitSurpassed.title": "ขีดจำกัดเตือนภัยเกิน",
  "warn.strings.limitSurpassed.description": "{user_mention} ได้ *เกิน* ขีดจำกัดคำเตือน ({limit}) โดยเพิ่งได้รับคำเตือนหมายเลข {number}",
  "warn.strings.limitSurpassedTimedOut.title": "ขีดจำกัดเตือนภัยเกิน",
  "warn.strings.limitSurpassedTimedOut.description": "{user_mention} ได้ *เกิน* ขีดจำกัดคำเตือน ({limit}) โดยเพิ่งได้รับคำเตือนหมายเลข {number} และต่อมาได้ถูกระงับชั่วคราวเป็นเวลา {period}",
  "music.name": "ดนตรี",
  "music.description": "อนุญาตให้ผู้ใช้จัดการการเล่นเพลงในช่องเสียง",
  "music.options.history.name": "ประวัติศาสตร์",
  "music.options.history.description": "แสดงรายการเพลงที่เคยเล่นมาก่อน",
  "music.options.history.strings.playbackHistory": "ประวัติการเล่นย้อนหลัง",
  "music.options.loop.name": "ลูป",
  "music.options.loop.description": "วนลูปเพลงที่กำลังเล่นอยู่",
  "music.options.loop.strings.noSong.title": "ไม่ได้เล่นเพลง",
  "music.options.loop.strings.noSong.description": "ไม่มีเพลงให้เล่นซ้ำ",
  "music.options.loop.strings.noSongCollection.title": "ไม่ได้เล่นคอลเลกชันเพลง",
  "music.options.loop.strings.noSongCollection.description.noSongCollection": "ไม่มีคอลเลกชันเพลงให้เล่นซ้ำ",
  "music.options.loop.strings.noSongCollection.description.trySongInstead": "ลองวนซ้ำเพลงปัจจุบันแทน",
  "music.options.loop.strings.enabled.title": "เปิดใช้งานลูป",
  "music.options.loop.strings.enabled.description.song": "เพลงปัจจุบันจะเล่นซ้ำ",
  "music.options.loop.strings.enabled.description.songCollection": "คอลเลกชันเพลงปัจจุบันจะเล่นซ้ำ",
  "music.options.loop.strings.disabled.title": "ลูปถูกปิดใช้งาน",
  "music.options.loop.strings.disabled.description.song": "เพลงปัจจุบันจะไม่เล่นซ้ำอีกต่อไป",
  "music.options.loop.strings.disabled.description.songCollection": "คอลเลกชันเพลงปัจจุบันจะไม่เล่นซ้ำอีกต่อไป",
  "music.options.now.name": "ตอนนี้",
  "music.options.now.description": "แสดงเพลงที่กำลังเล่นอยู่",
  "music.options.now.strings.noSong.title": "ไม่ได้เล่นเพลง",
  "music.options.now.strings.noSong.description": "ไม่มีเพลงที่จะแสดงข้อมูล",
  "music.options.now.strings.noSongCollection.title": "ไม่ได้เล่นคอลเลกชันเพลง",
  "music.options.now.strings.noSongCollection.description.noSongCollection": "ไม่มีคอลเลกชันเพลงที่จะแสดงข้อมูล",
  "music.options.now.strings.noSongCollection.description.trySongInstead": "ลองขอข้อมูลเกี่ยวกับเพลงที่กำลังเล่นอยู่แทน",
  "music.options.now.strings.nowPlaying": "กำลังเล่น",
  "music.options.now.strings.songs": "เพลง",
  "music.options.now.strings.collection": "การรวบรวม",
  "music.options.now.strings.track": "ติดตาม",
  "music.options.now.strings.title": "ชื่อเรื่อง",
  "music.options.now.strings.requestedBy": "ขอโดย",
  "music.options.now.strings.runningTime": "เวลาในการวิ่ง",
  "music.options.now.strings.playingSince": "ตั้งแต่ {relative_timestamp}",
  "music.options.now.strings.sourcedFrom": "รายการนี้มาจาก {แหล่งที่มา}",
  "music.options.now.strings.theInternet": "อินเทอร์เน็ต",
  "music.options.pause.name": "หยุดชั่วคราว",
  "music.options.pause.description": "หยุดชั่วคราวเพลงที่กำลังเล่นอยู่หรือคอลเลกชันเพลง",
  "music.options.pause.strings.paused.title": "หยุดชั่วคราว",
  "music.options.pause.strings.paused.description": "หยุดการเล่นเพลงชั่วคราว",
  "music.options.play.name": "เล่น",
  "music.options.play.description": "อนุญาตให้ผู้ใช้เล่นเพลงในช่องเสียง",
  "music.options.play.options.stream.name": "สตรีม",
  "music.options.play.options.stream.description": "เล่นสตรีมเสียง",
  "music.options.play.options.stream.options.url.name": "url",
  "music.options.play.options.stream.options.url.description": "ลิงก์ไปยังสตรีมเสียง",
  "music.options.play.options.youtube.name": "ยูทูบ",
  "music.options.play.options.youtube.description": "เล่นเพลงจาก YouTube",
  "music.options.play.strings.selectSong.title": "เลือกข้อมูล",
  "music.options.play.strings.selectSong.description": "เลือกเพลงหรือคอลเลกชันเพลงจากตัวเลือกด้านล่าง",
  "music.options.play.strings.stream": "สตรีมเสียง",
  "music.options.play.strings.notFound.title": "ไม่พบเพลง",
  "music.options.play.strings.notFound.description.notFound": "ไม่สามารถหาเพลงที่ขอได้",
  "music.options.play.strings.notFound.description.tryDifferentQuery": "คุณอาจลองค้นหาด้วยวิธีอื่น หรือขอเพลงอื่นได้",
  "music.options.play.strings.inDifferentVc.title": "บอทอยู่ในช่องทางอื่น",
  "music.options.play.strings.inDifferentVc.description": "บอทกำลังเล่นเพลงอยู่ในช่องเสียงอื่นแล้ว",
  "music.options.play.strings.queueFull.title": "คิวเต็มแล้ว",
  "music.options.play.strings.queueFull.description": "คิวเต็มแล้ว กรุณาลบเพลงออกจากคิวเพลง หรือข้ามเพลงปัจจุบันเพื่อเลื่อนคิวเพลงทันที หรือรอจนกว่าเพลงปัจจุบันจะเล่นจบ",
  "music.options.play.strings.queued.title": "รายการที่ค้างอยู่",
  "music.options.play.strings.queued.description.private": "รายการของคุณ, **{title}**, ได้ถูกเพิ่มเข้าไปในคิวแล้ว.",
  "music.options.play.strings.queued.description.public": "**{title}** ถูกเพิ่มเข้าไปในคิวตามคำขอของ {user_mention}.",
  "music.options.play.strings.failedToLoad.title": "ไม่สามารถโหลดแทร็กได้",
  "music.options.play.strings.failedToLoad.description": "แทร็ก **{title}** ไม่สามารถโหลดได้",
  "music.options.play.strings.failedToPlay.title": "ไม่สามารถเล่นแทร็กได้",
  "music.options.play.strings.failedToPlay.description": "เพลง **{ชื่อเพลง}** ไม่สามารถเล่นได้",
  "music.options.play.strings.nowPlaying.title.nowPlaying": "กำลังเล่น {listing_type}",
  "music.options.play.strings.nowPlaying.title.type.song": "เพลง",
  "music.options.play.strings.nowPlaying.title.type.songCollection": "คอลเลกชันเพลง",
  "music.options.play.strings.nowPlaying.title.type.stream": "สตรีมเสียง",
  "music.options.play.strings.nowPlaying.description.nowPlaying": "กำลังเล่น {song_information} [**{title}**]({url}) ตามคำขอของ {user_mention}.",
  "music.options.play.strings.nowPlaying.description.track": "แทร็ก **{index}/{number}** ของ **{title}**: ",
  "music.options.queue.name": "คิว",
  "music.options.queue.description": "แสดงรายการเพลงที่อยู่ในคิว",
  "music.options.queue.strings.queue": "คิว",
  "music.options.remove.name": "ลบ",
  "music.options.remove.description": "ลบรายการเพลงออกจากคิว",
  "music.options.remove.strings.queueEmpty.title": "คิวว่าง",
  "music.options.remove.strings.queueEmpty.description": "ไม่มีเพลงในคิว",
  "music.options.remove.strings.selectSong.title": "เลือกข้อมูล",
  "music.options.remove.strings.selectSong.description": "เลือกเพลงหรือคอลเลกชันเพลงที่ต้องการลบออกจากตัวเลือกด้านล่าง",
  "music.options.remove.strings.failed.title": "ไม่สามารถลบเพลงได้",
  "music.options.remove.strings.failed.description": "เนื่องจากสาเหตุที่ไม่ทราบได้ การนำเพลงที่เลือกออกจากคิวล้มเหลว",
  "music.options.remove.strings.removed.title": "ถูกลบแล้ว",
  "music.options.remove.strings.removed.description": "เพลง **{ชื่อเพลง}** ได้ถูกลบโดย {ชื่อผู้ใช้}.",
  "music.options.replay.name": "เล่นซ้ำ",
  "music.options.replay.description": "เริ่มเล่นเพลงที่กำลังเล่นอยู่จากต้นเพลง",
  "music.options.replay.strings.noSong.title": "ไม่มีเพลงให้เล่นซ้ำ",
  "music.options.replay.strings.noSong.description": "ไม่มีเพลงให้เล่นซ้ำ",
  "music.options.replay.strings.noSongCollection.title": "ไม่มีคอลเลกชันเพลงให้เล่นซ้ำ",
  "music.options.replay.strings.noSongCollection.description.noSongCollection": "ไม่มีคอลเลกชันเพลงให้เล่นซ้ำ",
  "music.options.replay.strings.noSongCollection.description.trySongInstead": "ลองเล่นเพลงปัจจุบันซ้ำแทน",
  "music.options.replay.strings.replaying.title": "เล่นซ้ำ",
  "music.options.replay.strings.replaying.description": "เพลงปัจจุบันจะเล่นอีกครั้ง",
  "music.options.resume.name": "ประวัติย่อ",
  "music.options.resume.description": "หยุดชั่วคราวเพลงที่กำลังเล่นอยู่หากเพลงนั้นถูกหยุดชั่วคราว",
  "music.options.resume.strings.noSong.title": "ไม่มีเพลงที่จะเล่นต่อ",
  "music.options.resume.strings.noSong.description": "ไม่มีเพลงที่จะเล่นต่อ",
  "music.options.resume.strings.notPaused.title": "เพลงไม่หยุดชั่วคราว",
  "music.options.resume.strings.notPaused.description": "เพลงปัจจุบันไม่ได้หยุดชั่วคราว",
  "music.options.resume.strings.resumed.title": "กลับมาดำเนินการต่อ",
  "music.options.resume.strings.resumed.description": "การเล่นเพลงได้กลับมาดำเนินการต่อแล้ว",
  "music.options.skip-to.name": "ข้ามไปที่",
  "music.options.skip-to.description": "ข้ามไปยังจุดที่กำหนดในเพลงที่กำลังเล่นอยู่",
  "music.options.skip-to.strings.noSong.title": "ไม่มีเพลงเพื่อค้นหาเวลา",
  "music.options.skip-to.strings.noSong.description": "ไม่มีเพลงที่จะค้นหาเวลาที่ระบุ",
  "music.options.skip-to.strings.invalidTimestamp.title": "เวลาไม่ถูกต้อง",
  "music.options.skip-to.strings.invalidTimestamp.description": "เวลาที่คุณระบุไม่ถูกต้อง",
  "music.options.skip-to.strings.skippedTo.title": "ข้ามไปยังตำแหน่งเวลา",
  "music.options.skip-to.strings.skippedTo.description": "การเล่นได้ข้ามไปยังตำแหน่งเวลาที่ระบุ",
  "music.options.fast-forward.name": "กรอไปข้างหน้า",
  "music.options.fast-forward.description": "กรอเพลงไปข้างหน้าตามระยะเวลาที่กำหนด",
  "music.options.fast-forward.strings.noSong.title": "ไม่มีเพลงให้กดข้าม",
  "music.options.fast-forward.strings.noSong.description": "ไม่มีเพลงให้เร่งความเร็ว",
  "music.options.fast-forward.strings.invalidTimestamp.title": "เวลาไม่ถูกต้อง",
  "music.options.fast-forward.strings.invalidTimestamp.description": "เวลาที่คุณระบุไม่ถูกต้อง",
  "music.options.fast-forward.strings.fastForwarded.title": "กรอไปข้างหน้า",
  "music.options.fast-forward.strings.fastForwarded.description": "การเล่นได้ข้ามไปเป็นจำนวนเวลาที่กำหนดไว้",
  "music.options.rewind.name": "ย้อนกลับ",
  "music.options.rewind.description": "ย้อนกลับเพลงเป็นระยะเวลาที่กำหนด",
  "music.options.rewind.strings.noSong.title": "ไม่มีเพลงให้ย้อนกลับ",
  "music.options.rewind.strings.noSong.description": "ไม่มีเพลงให้ย้อนกลับ",
  "music.options.rewind.strings.invalidTimestamp.title": "เวลาไม่ถูกต้อง",
  "music.options.rewind.strings.invalidTimestamp.description": "เวลาที่คุณระบุไม่ถูกต้อง",
  "music.options.rewind.strings.rewound.title": "ย้อนกลับ",
  "music.options.rewind.strings.rewound.description": "การเล่นได้ถูกย้อนกลับตามจำนวนเวลาที่กำหนด",
  "music.options.skip.name": "ข้าม",
  "music.options.skip.description": "ข้ามเพลงที่กำลังเล่นอยู่",
  "music.options.skip.strings.noSong.title": "ไม่มีเพลงให้ข้าม",
  "music.options.skip.strings.noSong.description": "ไม่มีเพลงให้ข้าม",
  "music.options.skip.strings.noSongCollection.title": "ไม่มีเพลงในคอลเลกชันที่ต้องข้าม",
  "music.options.skip.strings.noSongCollection.description.noSongCollection": "ไม่มีคอลเลกชันเพลงให้ข้าม",
  "music.options.skip.strings.noSongCollection.description.trySongInstead": "ลองข้ามเพลงปัจจุบันแทน",
  "music.options.skip.strings.skippedSong.title": "ข้าม",
  "music.options.skip.strings.skippedSong.description": "เพลงถูกข้ามไปแล้ว",
  "music.options.skip.strings.skippedSongCollection.title": "ข้าม",
  "music.options.skip.strings.skippedSongCollection.description": "เพลงในคอลเลกชันถูกข้ามไปแล้ว",
  "music.options.stop.name": "หยุด",
  "music.options.stop.description": "หยุดการฟังปัจจุบัน ล้างคิวและประวัติเพลง",
  "music.options.stop.strings.stopped.title": "หยุด",
  "music.options.stop.strings.stopped.description": "การฟังเพลงได้ถูกหยุดแล้ว และคิวเพลงกับประวัติการฟังได้ถูกล้างแล้ว",
  "music.options.unskip.name": "ข้าม",
  "music.options.unskip.description": "นำเพลงที่เล่นล่าสุดกลับมา",
  "music.options.unskip.strings.historyEmpty.title": "ประวัติว่างเปล่า",
  "music.options.unskip.strings.historyEmpty.description": "ไม่มีรายการเพลงที่จะนำกลับมา",
  "music.options.unskip.strings.noSongCollection.title": "ไม่มีเพลงในคอลเลกชันที่ต้องข้าม",
  "music.options.unskip.strings.noSongCollection.description.noSongCollection": "ไม่มีคอลเลกชันเพลงให้ข้าม",
  "music.options.unskip.strings.noSongCollection.description.trySongInstead": "ลองข้ามเพลงปัจจุบันแทน",
  "music.options.unskip.strings.queueFull.title": "คิวเต็มแล้ว",
  "music.options.unskip.strings.queueFull.description": "ไม่สามารถนำรายการเพลงที่เล่นล่าสุดกลับมาได้ เนื่องจากคิวเพลงเต็มแล้ว",
  "music.options.unskip.strings.unskipped.title": "ไม่ข้าม",
  "music.options.unskip.strings.unskipped.description": "รายการเพลงที่เล่นล่าสุดได้ถูกนำกลับมาแล้ว",
  "music.options.volume.name": "ปริมาณ",
  "music.options.volume.description": "อนุญาตให้ผู้ใช้จัดการระดับเสียงของการเล่นเพลง",
  "music.options.volume.options.display.name": "แสดง",
  "music.options.volume.options.display.description": "แสดงระดับเสียงของการเล่น",
  "music.options.volume.options.display.strings.volume.title": "ปริมาณ",
  "music.options.volume.options.display.strings.volume.description": "ปริมาณปัจจุบันคือ {ปริมาณ}%",
  "music.options.volume.options.set.name": "ตั้ง",
  "music.options.volume.options.set.description": "ตั้งค่าระดับเสียงในการเล่น",
  "music.options.volume.options.set.options.volume.name": "ปริมาณ",
  "music.options.volume.options.set.options.volume.description": "ปริมาณที่ต้องการตั้งค่า",
  "music.options.volume.options.set.strings.invalid.title": "ปริมาตรไม่ถูกต้อง",
  "music.options.volume.options.set.strings.invalid.description": "ระดับเสียงเพลงอาจไม่เป็นค่าลบ และอาจไม่สูงกว่า {ระดับเสียง}%",
  "music.options.volume.options.set.strings.set.title": "ชุดปริมาณ",
  "music.options.volume.options.set.strings.set.description": "ระดับเสียงถูกตั้งค่าไว้ที่ {ระดับเสียง}%",
  "music.strings.notPlaying.title": "ไม่ได้เล่นเพลง",
  "music.strings.notPlaying.description.toManage": "เพื่อจัดการการเล่น ให้ขอเพลงก่อน",
  "music.strings.notPlaying.description.toCheck": "เพื่อตรวจสอบข้อมูลที่เกี่ยวข้องกับการเล่น ให้ขอเพลงก่อน",
  "music.strings.notInVc.title": "ไม่อยู่ในช่องเสียง",
  "music.strings.notInVc.description.toManage": "ในการจัดการเพลง คุณต้องอยู่ในช่องเสียง",
  "music.strings.notInVc.description.toCheck": "เพื่อตรวจสอบข้อมูลที่เกี่ยวข้องกับการเล่นเสียง คุณต้องอยู่ในช่องเสียง",
  "music.strings.listings": "รายการ",
  "music.strings.listEmpty": "รายการนี้ว่างเปล่า",
  "music.strings.skips.tooManyArguments.title": "มีการข้ามอาร์กิวเมนต์มากเกินไป",
  "music.strings.skips.tooManyArguments.description": "คุณไม่สามารถข้าม __by__ จำนวนเพลงและข้ามไปยัง __to__ เพลงใดเพลงหนึ่งในคำสั่งเดียวกันได้",
  "music.strings.skips.invalid.title": "หมายเลขไม่ถูกต้อง",
  "music.strings.skips.invalid.description": "หมายเลขที่คุณป้อนไม่ถูกต้อง",
  "music.strings.outage.halted.title": "การเล่นเสียงหยุดชั่วคราว",
  "music.strings.outage.halted.description.outage": "รอสต์กำลังประสบปัญหาชั่วคราวเกี่ยวกับการเชื่อมต่อเสียง",
  "music.strings.outage.halted.description.noLoss": "ไม่ต้องกังวล: หากคุณกำลังฟังอยู่ เซสชันของคุณยังคงทำงานอยู่ และจะกลับมาใช้งานได้อีกครั้งทันทีที่การเชื่อมต่อถูกสร้างขึ้นใหม่",
  "music.strings.outage.cannotManage.title": "การเล่นเสียงถูกหยุดชั่วคราว",
  "music.strings.outage.cannotManage.description.outage": "การเล่นเสียงถูกหยุดชั่วคราวเนื่องจากเกิดการขัดจังหวะเสียงชั่วคราว",
  "music.strings.outage.cannotManage.description.backUpSoon": "คุณจะสามารถจัดการเพลงได้เมื่อการเชื่อมต่อเสียงได้รับการเชื่อมต่อใหม่",
  "music.strings.outage.restored.title": "การเล่นเสียงกลับมาทำงานต่อ",
  "music.strings.outage.restored.description": "การเชื่อมต่อเสียงได้รับการกู้คืนแล้ว",
  "suggestion.name": "ข้อเสนอแนะ",
  "suggestion.description": "อนุญาตให้ผู้ใช้เสนอแนะสำหรับชุมชน",
  "suggestion.strings.sent.title": "ส่งข้อเสนอแนะแล้ว!",
  "suggestion.strings.sent.description": "ข้อเสนอแนะของคุณได้ถูกส่งต่อไปยังทีมงานเซิร์ฟเวอร์แล้ว",
  "suggestion.strings.failed.title": "ไม่สามารถส่งคำแนะนำได้",
  "suggestion.strings.failed.description": "เนื่องจากสาเหตุที่ไม่ทราบได้ การส่งคำแนะนำของคุณล้มเหลว",
  "suggestion.strings.sureToCancel.title": "แน่ใจว่าจะออกหรือไม่?",
  "suggestion.strings.sureToCancel.description": "คุณแน่ใจหรือไม่ว่าต้องการหยุดส่งข้อเสนอแนะของคุณ?",
  "suggestion.strings.tooMany.title": "ข้อเสนอแนะมากเกินไป",
  "suggestion.strings.tooMany.description": "คุณได้เสนอแนะไปบ้างแล้วในระยะหลัง คุณควรรอสักครู่ก่อนที่จะเสนอแนะอีกครั้ง",
  "resource.name": "ทรัพยากร",
  "resource.description": "อนุญาตให้ผู้ใช้ส่งทรัพยากร",
  "resource.strings.sent.title": "ส่งทรัพยากรแล้ว!",
  "resource.strings.sent.description": "ทรัพยากรของคุณได้รับการส่งแล้ว",
  "resource.strings.failed.title": "ไม่สามารถส่งทรัพยากรได้",
  "resource.strings.failed.description": "เนื่องจากสาเหตุที่ไม่ทราบได้ การส่งทรัพยากรของคุณล้มเหลว",
  "resource.strings.sureToCancel.title": "แน่ใจว่าจะออกหรือไม่?",
  "resource.strings.sureToCancel.description": "คุณแน่ใจหรือไม่ว่าต้องการหยุดส่งทรัพยากรของคุณ?",
  "resource.strings.tooMany.title": "มีการส่งทรัพยากรมากเกินไป",
  "resource.strings.tooMany.description": "คุณได้ส่งทรัพยากรมาบ้างแล้วเมื่อเร็วๆ นี้ กรุณารอสักครู่ก่อนที่จะส่งอีกครั้ง",
  "ticket.name": "ตั๋ว",
  "ticket.description": "อนุญาตให้ผู้ใช้จัดการตั๋ว",
  "ticket.options.open.name": "เปิด",
  "ticket.options.open.description": "เปิดตั๋ว",
  "ticket.strings.sent.title": "เปิดตั๋วแล้ว!",
  "ticket.strings.sent.description": "มีการเปิดตั๋วแล้ว",
  "ticket.strings.failed.title": "ไม่สามารถเปิดตั๋วได้",
  "ticket.strings.failed.description": "เนื่องจากสาเหตุที่ไม่ทราบได้ ไม่สามารถเปิดตั๋วได้",
  "ticket.strings.sureToCancel.title": "แน่ใจว่าจะออกหรือไม่?",
  "ticket.strings.sureToCancel.description": "คุณแน่ใจหรือไม่ว่าคุณไม่ต้องการเปิดตั๋วอีกต่อไป?",
  "ticket.strings.tooMany.title": "ตั๋วเยอะเกินไป",
  "ticket.strings.tooMany.description": "คุณได้เปิดตั๋วไปแล้วเมื่อเร็วๆ นี้ คุณควรรอสักครู่ก่อนที่จะเปิดอีกใบหนึ่ง",
  "praise.name": "คำชม",
  "praise.description": "ชื่นชมผู้ใช้สำหรับการมีส่วนร่วมของพวกเขา",
  "praise.options.comment.name": "ความคิดเห็น",
  "praise.options.comment.description": "ความคิดเห็นที่จะแนบไปพร้อมกับการชมเชย",
  "praise.strings.praised.title": "ผู้ใช้ชื่นชม!",
  "praise.strings.praised.description": "คุณได้ชื่นชม {user_mention}",
  "praise.strings.cannotPraiseSelf.title": "ไม่สามารถสรรเสริญตนเอง",
  "praise.strings.cannotPraiseSelf.description": "คุณไม่สามารถชมเชยตัวเองได้",
  "praise.strings.failed.title": "ไม่สามารถชมเชยผู้ใช้ได้",
  "praise.strings.failed.description": "เนื่องจากสาเหตุที่ไม่ทราบได้ การยกย่องผู้ใช้ที่ระบุไว้ล้มเหลว",
  "praise.strings.tooMany.title": "คำชมมากเกินไป",
  "praise.strings.tooMany.description": "คุณได้ชื่นชมผู้ใช้ไปแล้วเมื่อเร็ว ๆ นี้ คุณต้องรอสักครู่ก่อนที่จะชื่นชมใครอีกครั้ง",
  "profile.name": "โปรไฟล์",
  "profile.description": "อนุญาตให้ผู้ใช้ดูข้อมูลเกี่ยวกับตนเองหรือผู้ใช้อื่น",
  "profile.options.roles.name": "บทบาท",
  "profile.options.roles.description": "เปิดเมนูเลือกบทบาท",
  "profile.options.roles.strings.limitReached.title": "ถึงขีดจำกัดบทบาท",
  "profile.options.roles.strings.limitReached.description.limitReached": "คุณได้ถึงขีดจำกัดของบทบาทที่สามารถมอบหมายได้ในหมวดหมู่นี้",
  "profile.options.roles.strings.limitReached.description.toChooseNew": "ในการเลือกบทบาทใหม่ ให้ยกเลิกการมอบหมายบทบาทที่มีอยู่ของคุณ",
  "profile.options.roles.strings.roleMandatory.title": "บทบาทนี้เป็นการบังคับ",
  "profile.options.roles.strings.roleMandatory.description": "คุณไม่สามารถยกเลิกการมอบหมายบทบาทนี้ได้ คุณสามารถสลับบทบาทนี้กับบทบาทอื่นจากหมวดหมู่เดียวกันเท่านั้น",
  "profile.options.roles.strings.chooseCategory": "เลือกหมวดหมู่",
  "profile.options.roles.strings.chooseRole": "เลือกบทบาท",
  "profile.options.roles.strings.back": "ย้อนกลับ",
  "profile.options.roles.strings.assigned": "ได้รับมอบหมาย",
  "profile.options.view.name": "มุมมอง",
  "profile.options.view.description": "แสดงโปรไฟล์ของผู้ใช้",
  "profile.options.view.strings.failed.title": "ไม่สามารถแสดงข้อมูลได้",
  "profile.options.view.strings.failed.description": "เนื่องจากสาเหตุที่ไม่ทราบได้ การแสดงข้อมูลเกี่ยวกับผู้ใช้ที่ระบุไว้ล้มเหลว",
  "profile.options.view.strings.information.title": "ข้อมูลเกี่ยวกับ {username}",
  "profile.options.view.strings.information.description.roles": "บทบาท",
  "profile.options.view.strings.information.description.dates": "วันที่",
  "profile.options.view.strings.information.description.statistics": "สถิติ",
  "profile.options.view.strings.information.description.received": "ได้รับ",
  "profile.options.view.strings.information.description.sent": "ส่งแล้ว",
  "profile.options.view.strings.information.description.praises": "คำสรรเสริญ",
  "profile.options.view.strings.information.description.warnings": "คำเตือน",
  "licence.name": "ใบอนุญาต",
  "licence.description": "อนุญาตให้ผู้ใช้ดูประกาศเกี่ยวกับข้อมูลและซอฟต์แวร์ที่ใช้โดยโครงการ Rost",
  "licence.options.software.name": "ซอฟต์แวร์",
  "licence.options.software.description": "ดูประกาศใบอนุญาตสำหรับซอฟต์แวร์ที่ใช้โดย Rost.",
  "licence.options.software.options.package.name": "แพ็กเกจ",
  "licence.options.software.options.package.description": "แพ็กเกจสำหรับดูใบอนุญาต",
  "licence.strings.invalid.title": "ใบอนุญาตไม่ถูกต้อง",
  "licence.strings.invalid.description": "ใบอนุญาตที่คุณพยายามดูนั้นไม่ถูกต้อง",
  "licence.strings.license": "ใบอนุญาต – {entity}",
  "licence.strings.source": "แหล่งที่มา",
  "licence.strings.copyright": "ประกาศลิขสิทธิ์",
  "credits.name": "เครดิต",
  "credits.description": "แสดงเมนูเครดิต",
  "credits.strings.translation": "การแปล",
  "acknowledgements.name": "คำขอบคุณ",
  "acknowledgements.description": "แสดงเมนูการขอบคุณ",
  "acknowledgements.strings.acknowledgements": "คำขอบคุณ"
}