{
  "notices.lastUpdate": "Última actualización: {fecha}",
  "notices.information.sections.guidelines.title": "Directrices",
  "notices.information.sections.learning.title": "Aprender",
  "notices.information.sections.learning.buttons.resources": "Recursos abiertos",
  "notices.information.sections.learning.buttons.resource": "Añadir recurso",
  "notices.information.sections.socials.buttons.website": "Página web",
  "notices.information.sections.socials.buttons.discord": "Discordia",
  "notices.information.sections.socials.buttons.instagram": "Instagram",
  "notices.information.sections.socials.buttons.github": "GitHub",
  "notices.information.sections.selfServe.title": "Autoservicio",
  "notices.information.sections.selfServe.buttons.roles": "Seleccionar funciones",
  "notices.information.sections.selfServe.buttons.suggestion": "Sugerir idea",
  "notices.information.sections.selfServe.buttons.report": "Denunciar usuario",
  "notices.information.sections.selfServe.buttons.ticket": "Billete abierto",
  "reports.users": "Usuarios denunciados",
  "reports.reason": "Motivo del informe",
  "reports.link": "Enlace al mensaje",
  "reports.noLinkProvided": "No se proporciona ningún enlace al mensaje.",
  "reports.previousInfractions": "Infracciones anteriores de {username}",
  "reports.noReports": "No hay informes de usuarios sin resolver.",
  "resources.noResources": "No se han presentado nuevos recursos.",
  "suggestion.suggestion": "Sugerencia",
  "suggestions.noSuggestions": "No hay sugerencias de nuevos servidores.",
  "tickets.noTickets": "No hay entradas abiertas.",
  "entryRequests.noEntryRequests": "No hay solicitudes sin resolver para entrar en el servidor.",
  "submittedBy": "Presentado por",
  "submittedAt": "Enviado a",
  "markResolved": "Marcar la incidencia como resuelta",
  "markUnresolved": "Marcar asunto como no resuelto",
  "alreadyMarkedResolved.title": "Ya marcado como resuelto",
  "alreadyMarkedResolved.description": "Este problema ya se ha marcado como resuelto.",
  "alreadyMarkedUnresolved.title": "Ya marcado como no resuelto",
  "alreadyMarkedUnresolved.description": "Esta cuestión ya se ha marcado como no resuelta.",
  "remove": "Eliminar",
  "cannotRemovePrompt.title": "No se puede eliminar el aviso",
  "cannotRemovePrompt.description": "No puede eliminar este aviso.",
  "close": "Cerrar",
  "cannotCloseIssue.title": "No se puede cerrar el problema",
  "cannotCloseIssue.description": "No se puede cerrar este tema.",
  "allUpToDate": "Todo al día",
  "antiFlood.floodDetectedAndTimedOut.title": "Inundación detectada",
  "antiFlood.floodDetectedAndTimedOut.description": "se ha detectado que {user_mention} está inundando el servidor, habiendo publicado {messages} en un lapso de {interval}, y posteriormente ha sido temporizado durante {duration}.",
  "antiFlood.floodDetectedAndTimedOut.description.messages.one": "{un} mensaje",
  "antiFlood.floodDetectedAndTimedOut.description.messages.two": "{dos} mensajes",
  "antiFlood.floodDetectedAndTimedOut.description.messages.many": "{muchos} mensajes"
}